pyonmi-1.0.dist-info/LICENSE.txt
pyonmi-1.0.dist-info/RECORD
pyonmi-1.0.dist-info/WHEEL
pyonmi-1.0.dist-info/METADATA
pyonmi-1.0.dist-info/LICENSE
pyonmi-1.0.dist-info/top_level.txt
pyonmi/__init__.py
pyonmi/pyonmi.cpython-36m-x86_64-linux-gnu.so
