Metadata-Version: 2.1
Name: pyonmi
Version: 1.0
Summary: a python module to calculate the overlaping NMI of two sets
Home-page: UNKNOWN
Author: Angel Panizo
Author-email: angel.panizo@upm.es
License: UNKNOWN
Platform: UNKNOWN
